{"type":"FeatureCollection","crs":{"type":"name","properties":{"name":"EPSG:4326"}},"features":[{"type":"Feature","id":1,"geometry":{"type":"Point","coordinates":[36.7820334999994,-1.29104969999998]},"properties":{"objectid":1,"globalid":"d1bf0a36-d661-427e-82ac-2a4ab3f7048e","VisitDate":"Mon, 01 Mar 2021 10:04:00 GMT","VisitBrief":"Visited a dentist at Royal Smiles in kilimani","SpecialistAvailable":"yes","SpecialistType":"Dentist","Note":null,"CreationDate":"Mon, 01 Mar 2021 10:07:29 GMT","Creator":"Risper_Mutuku_LearnArcGIS","EditDate":"Mon, 01 Mar 2021 10:07:29 GMT","Editor":"Risper_Mutuku_LearnArcGIS"}}]}